MANIFEST.in
README.txt
setup.cfg
setup.py
Refaction.egg-info/PKG-INFO
Refaction.egg-info/SOURCES.txt
Refaction.egg-info/dependency_links.txt
Refaction.egg-info/entry_points.txt
Refaction.egg-info/paste_deploy_config.ini_tmpl
Refaction.egg-info/paster_plugins.txt
Refaction.egg-info/requires.txt
Refaction.egg-info/top_level.txt
refaction/__init__.py
refaction/websetup.py
refaction/config/__init__.py
refaction/config/environment.py
refaction/config/middleware.py
refaction/config/routing.py
refaction/controllers/__init__.py
refaction/controllers/app.py
refaction/controllers/db.py
refaction/controllers/domain.py
refaction/controllers/error.py
refaction/controllers/roles.py
refaction/controllers/template.py
refaction/controllers/users.py
refaction/controllers/website.py
refaction/lib/__init__.py
refaction/lib/app_globals.py
refaction/lib/base.py
refaction/lib/helpers.py
refaction/lib/webfaction.py
refaction/model/__init__.py
refaction/public/pycrud.css
refaction/public/icons/delete.png
refaction/public/icons/details.png
refaction/public/icons/edit.png
refaction/public/icons/first.png
refaction/public/icons/last.png
refaction/public/icons/new.png
refaction/public/icons/next.png
refaction/public/icons/prev.png
refaction/public/icons/reply.png
refaction/public/icons/crystal_clear/add.png
refaction/public/icons/crystal_clear/back.png
refaction/public/icons/crystal_clear/cut.png
refaction/public/icons/crystal_clear/delete.png
refaction/public/icons/crystal_clear/edit.png
refaction/public/icons/crystal_clear/first.png
refaction/public/icons/crystal_clear/forward.png
refaction/public/icons/crystal_clear/info.png
refaction/public/icons/crystal_clear/last.png
refaction/public/icons/crystal_clear/new.png
refaction/public/icons/crystal_clear/next.png
refaction/public/icons/crystal_clear/playlist.png
refaction/public/icons/crystal_clear/prev.png
refaction/public/icons/crystal_clear/remove.png
refaction/public/icons/crystalsvg/mail_delete.png
refaction/public/icons/crystalsvg/mail_find.png
refaction/public/icons/crystalsvg/mail_forward.png
refaction/public/icons/crystalsvg/mail_generic.png
refaction/public/icons/crystalsvg/mail_get.png
refaction/public/icons/crystalsvg/mail_new.png
refaction/public/icons/crystalsvg/mail_post_to.png
