Metadata-Version: 1.0
Name: Refaction
Version: 0.0.1dev
Summary: Web-based interface for sharing webfaction services using webfaction's API.
Home-page: UNKNOWN
Author: Emanuel Calso
Author-email: egcalso@gmail.com
License: UNKNOWN
Platform: UNKNOWN
